pydepinject/__init__.py
pydepinject/backends.py
pydepinject-0.0.3.dev0.dist-info/licenses/LICENSE
pydepinject-0.0.3.dev0.dist-info/METADATA
pydepinject-0.0.3.dev0.dist-info/WHEEL
pydepinject-0.0.3.dev0.dist-info/top_level.txt
pydepinject-0.0.3.dev0.dist-info/RECORD
