Metadata-Version: 2.4
Name: pydepinject
Version: 0.0.3.dev0
Summary: A package to dynamically inject requirements into a virtual environment.
Author: pydepinject
License-Expression: MIT
Project-URL: homepage, https://github.com/pydepinject/pydepinject
Project-URL: documentation, https://github.com/pydepinject/pydepinject
Project-URL: repository, https://github.com/pydepinject/pydepinject
Keywords: virtualenv,requirements,dependency management
Classifier: Development Status :: 4 - Beta
Classifier: Intended Audience :: Developers
Classifier: Programming Language :: Python
Classifier: Programming Language :: Python :: 3 :: Only
Classifier: Programming Language :: Python :: 3
Classifier: Programming Language :: Python :: Implementation :: CPython
Classifier: Topic :: Software Development :: Libraries :: Python Modules
Classifier: Topic :: Software Development :: Libraries
Classifier: Typing :: Typed
Requires-Python: >=3.10
License-File: LICENSE
Requires-Dist: packaging>=23.0
Requires-Dist: typing-extensions>=4.4.0
Provides-Extra: lint
Requires-Dist: isort; extra == "lint"
Requires-Dist: pylint; extra == "lint"
Provides-Extra: test
Requires-Dist: pytest; extra == "test"
Requires-Dist: pytest-cov; extra == "test"
Requires-Dist: pytest-xdist; extra == "test"
Dynamic: license-file
